[
    {
        "limit": 0.9,
        "positive": 51,
        "true_positive": 7,
        "recall": 0.109375,
        "precition": 0.13725490196078433,
        "f_measure": 0.12173913043478261
    },
    {
        "limit": 0.85,
        "positive": 74,
        "true_positive": 25,
        "recall": 0.390625,
        "precition": 0.33783783783783783,
        "f_measure": 0.36231884057971014
    },
    {
        "limit": 0.8,
        "positive": 86,
        "true_positive": 28,
        "recall": 0.4375,
        "precition": 0.32558139534883723,
        "f_measure": 0.37333333333333335
    },
    {
        "limit": 0.75,
        "positive": 94,
        "true_positive": 31,
        "recall": 0.484375,
        "precition": 0.32978723404255317,
        "f_measure": 0.3924050632911392
    },
    {
        "limit": 0.7,
        "positive": 110,
        "true_positive": 41,
        "recall": 0.640625,
        "precition": 0.37272727272727274,
        "f_measure": 0.47126436781609193
    },
    {
        "limit": 0.6,
        "positive": 150,
        "true_positive": 48,
        "recall": 0.75,
        "precition": 0.32,
        "f_measure": 0.44859813084112143
    },
    {
        "limit": 0.5,
        "positive": 248,
        "true_positive": 48,
        "recall": 0.75,
        "precition": 0.1935483870967742,
        "f_measure": 0.30769230769230765
    },
    {
        "limit": 0.4,
        "positive": 416,
        "true_positive": 48,
        "recall": 0.75,
        "precition": 0.11538461538461539,
        "f_measure": 0.19999999999999998
    },
    {
        "limit": 0.3,
        "positive": 698,
        "true_positive": 63,
        "recall": 0.984375,
        "precition": 0.09025787965616046,
        "f_measure": 0.16535433070866143
    },
    {
        "limit": 0.2,
        "positive": 816,
        "true_positive": 64,
        "recall": 1.0,
        "precition": 0.0784313725490196,
        "f_measure": 0.14545454545454545
    },
    {
        "limit": 0.1,
        "positive": 940,
        "true_positive": 64,
        "recall": 1.0,
        "precition": 0.06808510638297872,
        "f_measure": 0.12749003984063745
    }
]