[
    {
        "type": "DOCKER-FROM",
        "children": [
            {
                "type": "DOCKER-IMAGE-NAME",
                "value": "golang",
                "children": []
            },
            {
                "type": "DOCKER-IMAGE-TAG",
                "value": "1.10.3",
                "children": []
            }
        ]
    },
    {
        "type": "DOCKER-WORKDIR",
        "children": [
            {
                "type": "DOCKER-PATH",
                "value": "/go/src/github.com/kubeflow/xgboost-operator",
                "children": []
            }
        ]
    },
    {
        "type": "DOCKER-COPY",
        "children": [
            {
                "type": "DOCKER-COPY-TARGET",
                "children": [
                    {
                        "type": "DOCKER-PATH",
                        "value": "pkg/",
                        "children": []
                    }
                ]
            },
            {
                "type": "DOCKER-COPY-SOURCE",
                "children": [
                    {
                        "type": "DOCKER-PATH",
                        "value": "pkg/",
                        "children": []
                    }
                ]
            }
        ]
    },
    {
        "type": "DOCKER-COPY",
        "children": [
            {
                "type": "DOCKER-COPY-TARGET",
                "children": [
                    {
                        "type": "DOCKER-PATH",
                        "value": "cmd/",
                        "children": []
                    }
                ]
            },
            {
                "type": "DOCKER-COPY-SOURCE",
                "children": [
                    {
                        "type": "DOCKER-PATH",
                        "value": "cmd/",
                        "children": []
                    }
                ]
            }
        ]
    },
    {
        "type": "DOCKER-COPY",
        "children": [
            {
                "type": "DOCKER-COPY-TARGET",
                "children": [
                    {
                        "type": "DOCKER-PATH",
                        "value": "vendor/",
                        "children": []
                    }
                ]
            },
            {
                "type": "DOCKER-COPY-SOURCE",
                "children": [
                    {
                        "type": "DOCKER-PATH",
                        "value": "vendor/",
                        "children": []
                    }
                ]
            }
        ]
    },
    {
        "type": "DOCKER-RUN",
        "children": [
            {
                "type": "MAYBE-BASH",
                "value": "CGO_ENABLED=0 GOOS=linux GOARCH=amd64 go build -a -o manager github.com/kubeflow/xgboost-operator/cmd/manager",
                "children": []
            }
        ]
    },
    {
        "type": "DOCKER-FROM",
        "children": [
            {
                "type": "DOCKER-IMAGE-NAME",
                "value": "ubuntu",
                "children": []
            },
            {
                "type": "DOCKER-IMAGE-TAG",
                "value": "latest",
                "children": []
            }
        ]
    },
    {
        "type": "DOCKER-WORKDIR",
        "children": [
            {
                "type": "DOCKER-PATH",
                "value": "/",
                "children": []
            }
        ]
    },
    {
        "type": "DOCKER-COPY",
        "children": [
            {
                "type": "DOCKER-COPY-TARGET",
                "children": [
                    {
                        "type": "DOCKER-PATH",
                        "value": ".",
                        "children": []
                    }
                ]
            },
            {
                "type": "DOCKER-COPY-SOURCE",
                "children": [
                    {
                        "type": "DOCKER-PATH",
                        "value": "/go/src/github.com/kubeflow/xgboost-operator/manager",
                        "children": []
                    }
                ]
            }
        ]
    },
    {
        "type": "DOCKER-ENTRYPOINT",
        "children": [
            {
                "type": "DOCKER-ENTRYPOINT-EXECUTABLE",
                "value": "/manager",
                "children": []
            }
        ]
    }
]