[
    {
        "type": "DOCKER-FROM",
        "children": [
            {
                "type": "DOCKER-IMAGE-NAME",
                "value": "proxy_init",
                "children": []
            },
            {
                "type": "DOCKER-IMAGE-REPO",
                "value": "gcr.io",
                "children": []
            },
            {
                "type": "DOCKER-IMAGE-TAG",
                "value": "1.0.0-snapshot.2",
                "children": []
            }
        ]
    }
]