[
    {
        "type": "DOCKER-FROM",
        "children": [
            {
                "type": "DOCKER-IMAGE-NAME",
                "value": "python",
                "children": []
            },
            {
                "type": "DOCKER-IMAGE-TAG",
                "value": "2.7.13",
                "children": []
            }
        ]
    },
    {
        "type": "DOCKER-ADD",
        "children": [
            {
                "type": "DOCKER-ADD-TARGET",
                "children": [
                    {
                        "type": "DOCKER-PATH",
                        "value": "snippet.py",
                        "children": []
                    }
                ]
            },
            {
                "type": "DOCKER-ADD-SOURCE",
                "children": [
                    {
                        "type": "DOCKER-PATH",
                        "value": "snippet.py",
                        "children": []
                    }
                ]
            }
        ]
    },
    {
        "type": "DOCKER-RUN",
        "children": [
            {
                "type": "MAYBE-BASH",
                "value": "pip",
                "children": []
            }
        ]
    },
    {
        "type": "DOCKER-RUN",
        "children": [
            {
                "type": "MAYBE-BASH",
                "value": "pip",
                "children": []
            }
        ]
    },
    {
        "type": "DOCKER-RUN",
        "children": [
            {
                "type": "MAYBE-BASH",
                "value": "pip",
                "children": []
            }
        ]
    },
    {
        "type": "DOCKER-CMD",
        "children": [
            {
                "type": "DOCKER-CMD-ARG",
                "value": "python",
                "children": []
            },
            {
                "type": "DOCKER-CMD-ARG",
                "value": "snippet.py",
                "children": []
            }
        ]
    }
]