[
    {
        "children": [
            {
                "children": [],
                "type": "DOCKER-IMAGE-NAME:debian-base-amd64"
            },
            {
                "children": [],
                "type": "DOCKER-IMAGE-REPO:k8s.gcr.io"
            },
            {
                "children": [],
                "type": "DOCKER-IMAGE-TAG:1.0.0"
            }
        ],
        "type": "DOCKER-FROM"
    },
    {
        "children": [
            {
                "children": [
                    {
                        "children": [],
                        "type": "DOCKER-PATH"
                    }
                ],
                "type": "DOCKER-ADD-TARGET"
            },
            {
                "children": [
                    {
                        "children": [],
                        "type": "DOCKER-PATH"
                    }
                ],
                "type": "DOCKER-ADD-SOURCE"
            }
        ],
        "type": "DOCKER-ADD"
    },
    {
        "children": [
            {
                "children": [
                    {
                        "type": "ABS-MAYBE-PATH",
                        "children": []
                    },
                    {
                        "type": "ABS-PATH-RELATIVE",
                        "children": []
                    },
                    {
                        "type": "ABS-SINGLE-SPACE",
                        "children": []
                    }
                ],
                "type": "DOCKER-ENTRYPOINT-EXECUTABLE"
            }
        ],
        "type": "DOCKER-ENTRYPOINT"
    }
]