[
    {
        "children": [
            {
                "children": [],
                "type": "DOCKER-IMAGE-NAME:ubuntu-debootstrap"
            },
            {
                "children": [],
                "type": "DOCKER-IMAGE-TAG:14.04"
            }
        ],
        "type": "DOCKER-FROM"
    },
    {
        "children": [
            {
                "children": [
                    {
                        "type": "ABS-MAYBE-PATH",
                        "children": []
                    },
                    {
                        "type": "ABS-PATH-ABSOLUTE",
                        "children": []
                    }
                ],
                "type": "DOCKER-PATH"
            }
        ],
        "type": "DOCKER-VOLUME"
    },
    {
        "children": [
            {
                "children": [],
                "type": "DOCKER-PORT:80"
            }
        ],
        "type": "DOCKER-EXPOSE"
    },
    {
        "children": [
            {
                "children": [
                    {
                        "children": [
                            {
                                "children": [
                                    {
                                        "children": [],
                                        "type": "SC-APT-GET-UPDATE"
                                    }
                                ],
                                "type": "BASH-AND-MEM"
                            },
                            {
                                "children": [
                                    {
                                        "children": [
                                            {
                                                "children": [],
                                                "type": "SC-APT-GET-F-YES"
                                            }
                                        ],
                                        "type": "SC-APT-GET-DIST-UPGRADE"
                                    }
                                ],
                                "type": "BASH-AND-MEM"
                            },
                            {
                                "children": [
                                    {
                                        "children": [
                                            {
                                                "children": [],
                                                "type": "SC-APT-GET-F-YES"
                                            },
                                            {
                                                "children": [
                                                    {
                                                        "children": [],
                                                        "type": "BASH-LITERAL"
                                                    }
                                                ],
                                                "type": "SC-APT-GET-QUIET"
                                            },
                                            {
                                                "children": [
                                                    {
                                                        "children": [],
                                                        "type": "SC-APT-GET-PACKAGE:MINI-DINSTALL"
                                                    },
                                                    {
                                                        "children": [],
                                                        "type": "SC-APT-GET-PACKAGE:NGINX"
                                                    }
                                                ],
                                                "type": "SC-APT-GET-PACKAGES"
                                            }
                                        ],
                                        "type": "SC-APT-GET-INSTALL"
                                    }
                                ],
                                "type": "BASH-AND-MEM"
                            }
                        ],
                        "type": "BASH-AND-IF"
                    }
                ],
                "type": "BASH-SCRIPT"
            }
        ],
        "type": "DOCKER-RUN"
    },
    {
        "children": [
            {
                "children": [
                    {
                        "children": [
                            {
                                "type": "ABS-MAYBE-PATH",
                                "children": []
                            },
                            {
                                "type": "ABS-PATH-ABSOLUTE",
                                "children": []
                            }
                        ],
                        "type": "DOCKER-PATH"
                    }
                ],
                "type": "DOCKER-ADD-TARGET"
            },
            {
                "children": [
                    {
                        "children": [],
                        "type": "DOCKER-PATH"
                    }
                ],
                "type": "DOCKER-ADD-SOURCE"
            }
        ],
        "type": "DOCKER-ADD"
    },
    {
        "children": [
            {
                "children": [
                    {
                        "children": [
                            {
                                "type": "ABS-MAYBE-PATH",
                                "children": []
                            },
                            {
                                "type": "ABS-PATH-ABSOLUTE",
                                "children": []
                            }
                        ],
                        "type": "DOCKER-PATH"
                    }
                ],
                "type": "DOCKER-ADD-TARGET"
            },
            {
                "children": [
                    {
                        "children": [],
                        "type": "DOCKER-PATH"
                    }
                ],
                "type": "DOCKER-ADD-SOURCE"
            }
        ],
        "type": "DOCKER-ADD"
    },
    {
        "children": [
            {
                "children": [
                    {
                        "children": [
                            {
                                "type": "ABS-MAYBE-PATH",
                                "children": []
                            },
                            {
                                "type": "ABS-PROBABLY-URL",
                                "children": []
                            },
                            {
                                "type": "ABS-PATH-ABSOLUTE",
                                "children": []
                            }
                        ],
                        "type": "DOCKER-PATH"
                    }
                ],
                "type": "DOCKER-ADD-TARGET"
            },
            {
                "children": [
                    {
                        "children": [
                            {
                                "type": "ABS-PROBABLY-URL",
                                "children": []
                            }
                        ],
                        "type": "DOCKER-PATH"
                    }
                ],
                "type": "DOCKER-ADD-SOURCE"
            }
        ],
        "type": "DOCKER-ADD"
    },
    {
        "children": [
            {
                "children": [
                    {
                        "children": [
                            {
                                "children": [
                                    {
                                        "children": [
                                            {
                                                "children": [],
                                                "type": "BASH-LITERAL"
                                            },
                                            {
                                                "children": [],
                                                "type": "BASH-LITERAL"
                                            }
                                        ],
                                        "type": "BASH-CONCAT"
                                    }
                                ],
                                "type": "SC-CHMOD-MODE"
                            },
                            {
                                "children": [
                                    {
                                        "children": [
                                            {
                                                "children": [
                                                    {
                                                        "type": "ABS-MAYBE-PATH",
                                                        "children": []
                                                    },
                                                    {
                                                        "type": "ABS-PROBABLY-URL",
                                                        "children": []
                                                    },
                                                    {
                                                        "type": "ABS-PATH-ABSOLUTE",
                                                        "children": []
                                                    }
                                                ],
                                                "type": "BASH-LITERAL"
                                            }
                                        ],
                                        "type": "SC-CHMOD-PATH"
                                    }
                                ],
                                "type": "SC-CHMOD-PATHS"
                            }
                        ],
                        "type": "SC-CHMOD"
                    }
                ],
                "type": "BASH-SCRIPT"
            }
        ],
        "type": "DOCKER-RUN"
    },
    {
        "children": [
            {
                "children": [
                    {
                        "type": "ABS-MAYBE-PATH",
                        "children": []
                    },
                    {
                        "type": "ABS-PROBABLY-URL",
                        "children": []
                    },
                    {
                        "type": "ABS-PATH-ABSOLUTE",
                        "children": []
                    }
                ],
                "type": "DOCKER-CMD-ARG"
            }
        ],
        "type": "DOCKER-CMD"
    }
]